fireworks_livekit_voice_agent/__init__.py
fireworks_livekit_voice_agent/log.py
fireworks_livekit_voice_agent/py.typed
fireworks_livekit_voice_agent/version.py
fireworks_livekit_voice_agent/voice_agent_api/__init__.py
fireworks_livekit_voice_agent/voice_agent_api/voice_agent_api.py
fireworks_livekit_voice_agent-0.1.5.dist-info/METADATA
fireworks_livekit_voice_agent-0.1.5.dist-info/WHEEL
fireworks_livekit_voice_agent-0.1.5.dist-info/RECORD
